oasislmf-2.4.11.data/purelib/oasislmf/__init__.py
oasislmf-2.4.11.data/purelib/oasislmf/manager.py
oasislmf-2.4.11.data/purelib/oasislmf/_data/action_tree.p
oasislmf-2.4.11.data/purelib/oasislmf/_data/analysis_settings.json
oasislmf-2.4.11.data/purelib/oasislmf/_data/calc_rules_direct.csv
oasislmf-2.4.11.data/purelib/oasislmf/_data/calc_rules_direct_layer.csv
oasislmf-2.4.11.data/purelib/oasislmf/_data/calc_rules_step.csv
oasislmf-2.4.11.data/purelib/oasislmf/_data/config_compatibility_profile.json
oasislmf-2.4.11.data/purelib/oasislmf/_data/default_acc_profile.json
oasislmf-2.4.11.data/purelib/oasislmf/_data/default_combined_exposure_profile.json
oasislmf-2.4.11.data/purelib/oasislmf/_data/default_fm_agg_profile.json
oasislmf-2.4.11.data/purelib/oasislmf/_data/default_loc_profile.json
oasislmf-2.4.11.data/purelib/oasislmf/_data/default_step_policies_profile.json
oasislmf-2.4.11.data/purelib/oasislmf/_data/quantile.csv
oasislmf-2.4.11.data/purelib/oasislmf/cli/__init__.py
oasislmf-2.4.11.data/purelib/oasislmf/cli/admin.py
oasislmf-2.4.11.data/purelib/oasislmf/cli/api.py
oasislmf-2.4.11.data/purelib/oasislmf/cli/command.py
oasislmf-2.4.11.data/purelib/oasislmf/cli/config.py
oasislmf-2.4.11.data/purelib/oasislmf/cli/exposure.py
oasislmf-2.4.11.data/purelib/oasislmf/cli/model.py
oasislmf-2.4.11.data/purelib/oasislmf/cli/root.py
oasislmf-2.4.11.data/purelib/oasislmf/cli/test.py
oasislmf-2.4.11.data/purelib/oasislmf/cli/version.py
oasislmf-2.4.11.data/purelib/oasislmf/computation/__init__.py
oasislmf-2.4.11.data/purelib/oasislmf/computation/base.py
oasislmf-2.4.11.data/purelib/oasislmf/computation/data/__init__.py
oasislmf-2.4.11.data/purelib/oasislmf/computation/data/dummy_model/__init__.py
oasislmf-2.4.11.data/purelib/oasislmf/computation/data/dummy_model/generate.py
oasislmf-2.4.11.data/purelib/oasislmf/computation/generate/__init__.py
oasislmf-2.4.11.data/purelib/oasislmf/computation/generate/doc.py
oasislmf-2.4.11.data/purelib/oasislmf/computation/generate/files.py
oasislmf-2.4.11.dist-info/licenses/LICENSE
oasislmf-2.4.11.dist-info/METADATA
oasislmf-2.4.11.dist-info/WHEEL
oasislmf-2.4.11.dist-info/entry_points.txt
oasislmf-2.4.11.dist-info/top_level.txt
oasislmf-2.4.11.dist-info/RECORD
