Metadata-Version: 2.4
Name: oasislmf
Version: 2.4.11
Summary: Core loss modelling framework.
Home-page: https://github.com/OasisLMF/oasislmf
Author: Oasis LMF
Author-email: support@oasislmf.org
License: BSD 3-Clause
Keywords: oasis lmf loss modeling framework
Classifier: Development Status :: 4 - Beta
Classifier: License :: OSI Approved :: BSD License
Classifier: Operating System :: OS Independent
Classifier: Programming Language :: Python
Classifier: Programming Language :: Python :: 3.6
Requires-Python: >=3.6
License-File: LICENSE
Requires-Dist: anytree>=2.4.3
Requires-Dist: argparsetree>=0.0.5
Requires-Dist: chainmap
Requires-Dist: chardet
Requires-Dist: fastparquet>=0.3.1
Requires-Dist: msgpack
Requires-Dist: numba>=0.57.0
Requires-Dist: numexpr
Requires-Dist: numpy>=1.18
Requires-Dist: ods-tools>=4.0.5
Requires-Dist: oasis-data-manager>=0.1.1
Requires-Dist: pandas!=1.1.0,!=1.1.1,>=1.0.3
Requires-Dist: pyarrow>=15.0.0
Requires-Dist: pytz
Requires-Dist: requests-toolbelt
Requires-Dist: requests>=2.20.0
Requires-Dist: scipy
Requires-Dist: shutilwhich
Requires-Dist: tabulate>=0.8.2
Requires-Dist: tblib
Requires-Dist: tqdm
Requires-Dist: websocket-client>=1.8.0
Provides-Extra: extra
Requires-Dist: shapely>=1.3.0; extra == "extra"
Requires-Dist: geopandas; extra == "extra"
Requires-Dist: scikit-learn; extra == "extra"
Requires-Dist: rtree>=0.8.3; extra == "extra"
Requires-Dist: forex_python; extra == "extra"
Dynamic: author
Dynamic: author-email
Dynamic: classifier
Dynamic: description
Dynamic: description-content-type
Dynamic: home-page
Dynamic: keywords
Dynamic: license
Dynamic: license-file
Dynamic: provides-extra
Dynamic: requires-dist
Dynamic: requires-python
Dynamic: summary
